MANIFEST.in
README.md
pyproject.toml
hfortix_fortios-stubs/__init__.pyi
hfortix_fortios-stubs/client.pyi
hfortix_fortios-stubs/models.pyi
hfortix_fortios-stubs/py.typed
hfortix_fortios-stubs/api/__init__.pyi
hfortix_fortios-stubs/api/v2/__init__.pyi
hfortix_fortios-stubs/api/v2/cmdb/__init__.pyi
hfortix_fortios-stubs/api/v2/cmdb/alertemail/__init__.pyi
hfortix_fortios-stubs/api/v2/cmdb/alertemail/setting.pyi
hfortix_fortios-stubs/api/v2/cmdb/alertemail/_helpers/setting.pyi
hfortix_fortios-stubs/api/v2/cmdb/antivirus/__init__.pyi
hfortix_fortios-stubs/api/v2/cmdb/antivirus/exempt_list.pyi
hfortix_fortios-stubs/api/v2/cmdb/antivirus/profile.pyi
hfortix_fortios-stubs/api/v2/cmdb/antivirus/quarantine.pyi
hfortix_fortios-stubs/api/v2/cmdb/antivirus/settings.pyi
hfortix_fortios-stubs/api/v2/cmdb/antivirus/_helpers/exempt_list.pyi
hfortix_fortios-stubs/api/v2/cmdb/antivirus/_helpers/profile.pyi
hfortix_fortios-stubs/api/v2/cmdb/antivirus/_helpers/quarantine.pyi
hfortix_fortios-stubs/api/v2/cmdb/antivirus/_helpers/settings.pyi
hfortix_fortios-stubs/api/v2/cmdb/application/__init__.pyi
hfortix_fortios-stubs/api/v2/cmdb/application/custom.pyi
hfortix_fortios-stubs/api/v2/cmdb/application/group.pyi
hfortix_fortios-stubs/api/v2/cmdb/application/list.pyi
hfortix_fortios-stubs/api/v2/cmdb/application/name.pyi
hfortix_fortios-stubs/api/v2/cmdb/application/rule_settings.pyi
hfortix_fortios-stubs/api/v2/cmdb/application/_helpers/custom.pyi
hfortix_fortios-stubs/api/v2/cmdb/application/_helpers/group.pyi
hfortix_fortios-stubs/api/v2/cmdb/application/_helpers/list.pyi
hfortix_fortios-stubs/api/v2/cmdb/application/_helpers/name.pyi
hfortix_fortios-stubs/api/v2/cmdb/application/_helpers/rule_settings.pyi
hfortix_fortios-stubs/api/v2/cmdb/authentication/__init__.pyi
hfortix_fortios-stubs/api/v2/cmdb/authentication/rule.pyi
hfortix_fortios-stubs/api/v2/cmdb/authentication/scheme.pyi
hfortix_fortios-stubs/api/v2/cmdb/authentication/setting.pyi
hfortix_fortios_stubs.egg-info/PKG-INFO
hfortix_fortios_stubs.egg-info/SOURCES.txt
hfortix_fortios_stubs.egg-info/dependency_links.txt
hfortix_fortios_stubs.egg-info/not-zip-safe
hfortix_fortios_stubs.egg-info/top_level.txt