Metadata-Version: 2.4
Name: hfortix-fortios-stubs
Version: 0.5.9
Summary: Type stubs for hfortix-fortios - FortiOS SDK
Author-email: "Herman W. Jacobsen" <herman@wjacobsen.fo>
License: MIT
Project-URL: Homepage, https://github.com/hermanwjacobsen/hfortix
Project-URL: Repository, https://github.com/hermanwjacobsen/hfortix
Project-URL: Documentation, https://hfortix.readthedocs.io
Project-URL: Issues, https://github.com/hermanwjacobsen/hfortix/issues
Keywords: fortinet,fortigate,fortios,stubs,typing,type-hints,pyi
Classifier: Development Status :: 4 - Beta
Classifier: Intended Audience :: Developers
Classifier: Operating System :: OS Independent
Classifier: Programming Language :: Python :: 3
Classifier: Programming Language :: Python :: 3.10
Classifier: Programming Language :: Python :: 3.11
Classifier: Programming Language :: Python :: 3.12
Classifier: Programming Language :: Python :: 3.13
Classifier: Typing :: Typed
Classifier: Topic :: Software Development :: Libraries :: Python Modules
Requires-Python: >=3.10
